metrolopy/__init__.py
metrolopy/budget.py
metrolopy/builtin_constants.py
metrolopy/codata2018.py
metrolopy/constant.py
metrolopy/constcom.py
metrolopy/dfunc.py
metrolopy/distributions.py
metrolopy/exceptions.py
metrolopy/fit.py
metrolopy/functions.py
metrolopy/gummy.py
metrolopy/indexed.py
metrolopy/license.txt
metrolopy/logunit.py
metrolopy/mean.py
metrolopy/miscunits.py
metrolopy/nonlinearunit.py
metrolopy/nummy.py
metrolopy/offsetunit.py
metrolopy/pmethod.py
metrolopy/prefixedunit.py
metrolopy/printing.py
metrolopy/relunits.py
metrolopy/siunits.py
metrolopy/ummy.py
metrolopy/unit.py
metrolopy/unitparser.py
metrolopy/unitutils.py
metrolopy/usunits.py
metrolopy/version.py
metrolopy/tests/__init__.py
metrolopy/tests/common.py
metrolopy/tests/test_complex.py
metrolopy/tests/test_create.py
metrolopy/tests/test_gummy.py
metrolopy/tests/test_misc.py
metrolopy/tests/test_operations.py
metrolopy/tests/test_ubreakdown.py
metrolopy-1.0.1.dist-info/licenses/LICENSE
metrolopy-1.0.1.dist-info/METADATA
metrolopy-1.0.1.dist-info/WHEEL
metrolopy-1.0.1.dist-info/top_level.txt
metrolopy-1.0.1.dist-info/zip-safe
metrolopy-1.0.1.dist-info/RECORD
