Metadata-Version: 2.4
Name: metrolopy
Version: 1.0.1
Summary: tools for dealing with measured quantities: uncertainty propagation and unit conversion
Home-page: http://nrc-cnrc.github.io/MetroloPy/
Author: Harold Parks, National Research Council Canada
Author-email: parksh@nrc.ca
Classifier: Programming Language :: Python :: 3
Classifier: Operating System :: OS Independent
Classifier: Development Status :: 4 - Beta
Classifier: Framework :: Jupyter
Classifier: Framework :: IPython
Classifier: License :: OSI Approved :: GNU General Public License v3 (GPLv3)
Classifier: Intended Audience :: Science/Research
Classifier: Intended Audience :: Education
Classifier: Topic :: Scientific/Engineering :: Physics
Requires-Python: >=3.6
License-File: LICENSE
Requires-Dist: numpy>=1.13
Requires-Dist: scipy
Requires-Dist: matplotlib
Requires-Dist: pandas
Provides-Extra: pretty
Requires-Dist: IPython; extra == "pretty"
Dynamic: author
Dynamic: author-email
Dynamic: classifier
Dynamic: description
Dynamic: description-content-type
Dynamic: home-page
Dynamic: license-file
Dynamic: provides-extra
Dynamic: requires-dist
Dynamic: requires-python
Dynamic: summary
